alva_robot
