Metadata-Version: 1.0
Name: alva-robot
Version: 0.7.5
Summary: A robot base of AlvaIM
Home-page: https://alvaim.com
Author: Alexander.Li
Author-email: superpowerlee@gmail.com
License: GPL
Keywords: AlvaIM,Robot
Platform: UNKNOWN
